MANIFEST.in
requirements.txt
setup.cfg
setup.py
sphinx_measurement/__init__.py
sphinx_measurement.egg-info/PKG-INFO
sphinx_measurement.egg-info/SOURCES.txt
sphinx_measurement.egg-info/dependency_links.txt
sphinx_measurement.egg-info/requires.txt
sphinx_measurement.egg-info/top_level.txt
tests/__init__.py
tests/test_get_units.py