Metadata-Version: 1.1
Name: sphinx-measurement
Version: 0.1
Summary: Embed and convert measurements easily within your sphinx document.
Home-page: https://github.com/coddingtonbear/sphinx-measurement
Author: Adam Coddington
Author-email: me@adamcoddington.net
License: UNKNOWN
Platform: UNKNOWN
Classifier: License :: OSI Approved :: MIT License
Classifier: Operating System :: OS Independent
